contact_form/__init__.py
contact_form/apps.py
contact_form/conf.py
contact_form/helpers.py
contact_form/signals.py
contact_form/translation.py
contact_form/urls.py
contact_form/views.py
contact_form/admin/__init__.py
contact_form/admin/department.py
contact_form/admin/message.py
contact_form/admin/subject.py
contact_form/forms/__init__.py
contact_form/forms/bootstrap.py
contact_form/forms/bootstrap3.py
contact_form/forms/bootstrap4.py
contact_form/forms/uniform.py
contact_form/locale/fr/LC_MESSAGES/django.mo
contact_form/locale/fr/LC_MESSAGES/django.po
contact_form/locale/ru_RU/LC_MESSAGES/django.mo
contact_form/locale/ru_RU/LC_MESSAGES/django.po
contact_form/migrations/0001_initial.py
contact_form/migrations/0002_alter_field_ip_on_message.py
contact_form/migrations/0003_subject_order.py
contact_form/migrations/__init__.py
contact_form/models/__init__.py
contact_form/models/department.py
contact_form/models/message.py
contact_form/models/subject.py
contact_form/static/.keep
contact_form/templates/contact_form/form.html
contact_form/tests/__init__.py
contact_form/tests/base.py
contact_form/tests/runtests.py
contact_form/tests/test_contact_form.py
contact_form/tests/test_settings.py
contact_form/tests/urls.py
django_crispy_contact_form-0.3.8.dist-info/LICENSE.txt
django_crispy_contact_form-0.3.8.dist-info/METADATA
django_crispy_contact_form-0.3.8.dist-info/RECORD
django_crispy_contact_form-0.3.8.dist-info/WHEEL
django_crispy_contact_form-0.3.8.dist-info/top_level.txt
