Metadata-Version: 2.1
Name: django-crispy-contact-form
Version: 0.3.8
Summary: Customizable contact form based on crispy-forms with captcha support for Django 1.11+
Home-page: https://github.com/dlancer/django-crispy-contact-form
Author: dlancer
Author-email: dmdpost@gmail.com
Maintainer: dlancer
Maintainer-email: dmdpost@gmail.com
License: BSD
Platform: UNKNOWN
Classifier: Environment :: Web Environment
Classifier: Framework :: Django
Classifier: Intended Audience :: Developers
Classifier: License :: OSI Approved :: BSD License
Classifier: Operating System :: OS Independent
Classifier: Programming Language :: Python
Classifier: Programming Language :: Python :: 2.7
Classifier: Programming Language :: Python :: 3.4
Classifier: Programming Language :: Python :: 3.5
Classifier: Programming Language :: Python :: 3.6
Classifier: Topic :: Internet :: WWW/HTTP
Classifier: Topic :: Internet :: WWW/HTTP :: Dynamic Content
Classifier: Development Status :: 4 - Beta
Requires-Dist: Django (<2.2,>=1.11)
Requires-Dist: django-appcore (>=0.0.9)
Requires-Dist: django-crispy-forms (>=1.7.2)
Requires-Dist: django-ipware (>=2.1.0)
Requires-Dist: bleach (<3.0,>=2.1.4)
